ezpl/__init__.py
ezpl/ezpl.py
ezpl/cli/__init__.py
ezpl/cli/main.py
ezpl/cli/commands/__init__.py
ezpl/cli/commands/config.py
ezpl/cli/commands/info.py
ezpl/cli/commands/logs.py
ezpl/cli/commands/version.py
ezpl/cli/utils/__init__.py
ezpl/cli/utils/env_manager.py
ezpl/cli/utils/log_parser.py
ezpl/cli/utils/log_stats.py
ezpl/config/__init__.py
ezpl/config/defaults.py
ezpl/config/manager.py
ezpl/core/__init__.py
ezpl/core/exceptions.py
ezpl/core/interfaces.py
ezpl/handlers/__init__.py
ezpl/handlers/console.py
ezpl/handlers/file.py
ezpl/handlers/utils.py
ezpl/handlers/wizard/__init__.py
ezpl/handlers/wizard/core.py
ezpl/handlers/wizard/dynamic.py
ezpl/handlers/wizard/json.py
ezpl/handlers/wizard/panels.py
ezpl/handlers/wizard/progress.py
ezpl/handlers/wizard/tables.py
ezpl/types/__init__.py
ezpl/types/enums/__init__.py
ezpl/types/enums/log_level.py
ezpl/types/enums/patterns.py
ezpl/types/protocols/__init__.py
ezpl/types/protocols/logger_protocol.py
ezpl/types/protocols/printer_protocol.py
ezpl/utils/__init__.py
ezplog-1.5.0.dist-info/licenses/LICENSE
ezplog-1.5.0.dist-info/METADATA
ezplog-1.5.0.dist-info/WHEEL
ezplog-1.5.0.dist-info/entry_points.txt
ezplog-1.5.0.dist-info/top_level.txt
ezplog-1.5.0.dist-info/RECORD
