Metadata-Version: 2.4
Name: ezplog
Version: 1.5.0
Summary: Modern Python logging framework with Rich console output and loguru file logging, featuring advanced display capabilities, configuration management, and a simple typed API.
Author: Neuraaak
Maintainer: Neuraaak
License: MIT
Project-URL: Homepage, https://github.com/neuraaak/ezplog
Project-URL: Repository, https://github.com/neuraaak/ezplog
Project-URL: PyPI, https://pypi.org/project/ezplog/
Keywords: logging,rich,loguru,console,file,framework,cli
Classifier: Programming Language :: Python :: 3
Classifier: Programming Language :: Python :: 3.10
Classifier: Programming Language :: Python :: 3.11
Classifier: Programming Language :: Python :: 3.12
Classifier: Programming Language :: Python :: 3.13
Classifier: License :: OSI Approved :: MIT License
Classifier: Operating System :: OS Independent
Classifier: Development Status :: 5 - Production/Stable
Classifier: Intended Audience :: Developers
Classifier: Topic :: Software Development :: Libraries :: Python Modules
Classifier: Topic :: System :: Logging
Classifier: Topic :: Utilities
Requires-Python: >=3.10
License-File: LICENSE
Requires-Dist: loguru>=0.7.2
Requires-Dist: rich>=13.0.0
Requires-Dist: click>=8.0.0
Provides-Extra: dev
Requires-Dist: black>=23.0.0; extra == "dev"
Requires-Dist: isort>=5.12.0; extra == "dev"
Requires-Dist: ruff>=0.1.0; extra == "dev"
Requires-Dist: ty>=0.0.13; extra == "dev"
Requires-Dist: pyright>=1.1.0; extra == "dev"
Requires-Dist: pre-commit>=3.0.0; extra == "dev"
Requires-Dist: bandit>=1.7.0; extra == "dev"
Requires-Dist: pytest>=7.0.0; extra == "dev"
Requires-Dist: pytest-cov>=4.0.0; extra == "dev"
Requires-Dist: pytest-mock>=3.10.0; extra == "dev"
Requires-Dist: pytest-xdist>=3.0.0; extra == "dev"
Requires-Dist: build>=1.0.0; extra == "dev"
Requires-Dist: twine>=4.0.0; extra == "dev"
Provides-Extra: test
Requires-Dist: pytest>=7.0.0; extra == "test"
Requires-Dist: pytest-cov>=4.0.0; extra == "test"
Requires-Dist: pytest-mock>=3.10.0; extra == "test"
Requires-Dist: pytest-xdist>=3.0.0; extra == "test"
Dynamic: license-file
